apiport/__init__.py
apiport/cli.py
apiport/commands.py
apiport/encryption.py
apiport/storage.py
apiport-0.1.5.dist-info/licenses/LICENSE
apiport-0.1.5.dist-info/METADATA
apiport-0.1.5.dist-info/WHEEL
apiport-0.1.5.dist-info/entry_points.txt
apiport-0.1.5.dist-info/top_level.txt
apiport-0.1.5.dist-info/RECORD
