Metadata-Version: 2.4
Name: apiport
Version: 0.1.5
Summary: CLI tool for managing API secrets
Home-page: https://github.com/michniks2001/code-coffee-hack
Author: Samuel Michnik
Author-email: Samuel Michnik <michniksamuel@gmail.com>, Vikas Rawat <vikasrawcoder@gmail.com>
License: MIT
Project-URL: Homepage, https://github.com/michniks2001/code-coffee-hack
Project-URL: Bug Tracker, https://github.com/michniks2001/code-coffee-hack/issues
Classifier: Programming Language :: Python :: 3
Classifier: License :: OSI Approved :: MIT License
Classifier: Operating System :: OS Independent
Requires-Python: >=3.6
License-File: LICENSE
Requires-Dist: cryptography>=45.0.0
Requires-Dist: python-dotenv>=1.0.0
Provides-Extra: ai
Requires-Dist: google-generativeai>=0.3.0; extra == "ai"
Dynamic: author
Dynamic: home-page
Dynamic: license-file
Dynamic: requires-python
